<?xml version="1.0" encoding="UTF-8"?>
<Scene name="Shiny Scene" version="42" author="Norby">
    <Models>
        <Model name="floor" path="models/floor.obj"/>
        <Model name="menger" path="models/menger.obj"/>
        <Model name="mengerplat" path="models/mengerplat.obj"/>
        <Model name="octonorm" path="models/octonorm.obj"/>
        <Model name="sink" path="models/sink.obj"/>
        <Model name="sphere" path="models/sphere.obj"/>
        <Model name="suzanne" path="models/suzanne.obj"/>
    </Models>
    <Objects>
        <Object name="menger" model="menger" x="0" y="-3" z="0" rx="0" ry="0" rz="0" sx="1" sy="1" sz="1"/>
        <Object name="mengerplat" model="mengerplat" x="-1" y="2.9" z="10.9" rx="0" ry="0" rz="0" sx="1" sy="1" sz="1"/>
        <Object name="octonorm" model="octonorm" x="-3.6" y="7.6" z="0" rx="0" ry="50" rz="0" sx="1" sy="1" sz="1"/>
    </Objects>
    <Events>
        <Event key="animDown" condition="([bool]{switch}=[bool]{TRUE})&amp;([bool]{moveUp}=[bool]{TRUE})" actionType="copy" valSrc="downValue" valDst="pos"/>
        <Event key="animUp" condition="([bool]{switch}=[bool]{TRUE})&amp;([bool]{moveUp}=[bool]{FALSE})" actionType="copy" valSrc="upValue" valDst="pos"/>
        <Event key="count" condition="[bool]{TRUE}=[bool]{TRUE}" actionType="arithmetical" operationType="+" dataType="float" valA="count" valB="DELTA_TIME" valDst="count"/>
        <Event key="isTimeOverflow" condition="[float]{count}&gt;[float]{AnimTime}" actionType="flip" val="timeOverflow"/>
        <Event key="resetTime" condition="[bool]{timeOverflow}=[bool]{TRUE}" actionType="flip" val="timeOverflow"/>
        <Event key="resetTime2" condition="[bool]{timeOverflow}=[bool]{TRUE}" actionType="copy" valSrc="zero" valDst="count"/>
        <Event key="resetTime3" condition="[bool]{timeOverflow}=[bool]{TRUE}" actionType="flip" val="switch"/>
        <Event key="switch" condition="[bool]{switch}=[bool]{TRUE}" actionType="flip" val="switch"/>
        <Event key="switchMove" condition="[bool]{switch}=[bool]{TRUE}" actionType="flip" val="moveUp"/>
    </Events>
    <Attributes>
        <Attribute key="AnimTime" type="float" value="4"/>
        <Attribute key="DELTA_TIME" type="float" value="0"/>
        <Attribute key="FALSE" type="bool" value="false"/>
        <Attribute key="PLAYER_POSITION" type="vector" x="0" y="0" z="0"/>
        <Attribute key="TIME" type="float" value="0"/>
        <Attribute key="TRUE" type="bool" value="true"/>
        <Attribute key="count" type="float" value="0"/>
        <Attribute key="downValue" type="vector" x="-1" y="0" z="11"/>
        <Attribute key="moveUp" type="bool" value="false"/>
        <Attribute key="pos" type="vector" x="-1" y="0" z="11"/>
        <Attribute key="switch" type="bool" value="true"/>
        <Attribute key="timeOverflow" type="bool" value="false"/>
        <Attribute key="upValue" type="vector" x="-1" y="3" z="11"/>
        <Attribute key="zero" type="float" value="0"/>
    </Attributes>
    <Animators>
        <Animator type="position" time="4" interpolation="trigonometric" key="pos" object="mengerplat"/>
    </Animators>
    <DirectionalLight x="0.3" y="1" z="0.3" r="1" g="1" b="1"/>
    <Player x="0" y="0" z="0"/>
</Scene>
